drf_pretty_exception_handler/__init__.py
drf_pretty_exception_handler/drf_pretty_exception_handler.py
drf_pretty_exception_handler-0.1.3.dist-info/AUTHORS.rst
drf_pretty_exception_handler-0.1.3.dist-info/LICENSE
drf_pretty_exception_handler-0.1.3.dist-info/METADATA
drf_pretty_exception_handler-0.1.3.dist-info/WHEEL
drf_pretty_exception_handler-0.1.3.dist-info/top_level.txt
drf_pretty_exception_handler-0.1.3.dist-info/RECORD
