Metadata-Version: 2.1
Name: drf-pretty-exception-handler
Version: 0.1.3
Summary: Django Rest Framework pretty exception handler
Home-page: https://github.com/ivlevdenis/drf_pretty_exception_handler
Author: Denis Ivlev
Author-email: me@dierz.pro
License: MIT license
Keywords: drf_pretty_exception_handler
Platform: UNKNOWN
Classifier: Development Status :: 2 - Pre-Alpha
Classifier: Intended Audience :: Developers
Classifier: License :: OSI Approved :: MIT License
Classifier: Natural Language :: English
Classifier: Programming Language :: Python :: 3
Classifier: Programming Language :: Python :: 3.5
Classifier: Programming Language :: Python :: 3.6
Classifier: Programming Language :: Python :: 3.7
Classifier: Programming Language :: Python :: 3.8
Requires-Python: >=3.5
Requires-Dist: djangorestframework (>=3.10)
